{
    "caption": "\u00a7.001.Esercizio_1",
    "order": 1,
    "type": "sheet",
    "sheet": "sheet.mxl",
    "practice": false,
    "shot": [
        0,
        0,
        0,
        0,
        0,
        0,
        0,
        0,
        0,
        0,
        0,
        0,
        0,
        0,
        0
    ],
    "fail": [
        0,
        0,
        0,
        0,
        0,
        0,
        0,
        0,
        0,
        0,
        0,
        0,
        0,
        0,
        0
    ],
    "done": [
        0,
        0,
        0,
        0,
        0,
        0,
        0,
        0,
        0,
        0,
        0,
        0,
        0,
        0,
        0
    ]
}